visual_md/2.EDA.ipynb
visual_md/2.EDA_files/2.EDA_11_0.png
visual_md/2.EDA_files/2.EDA_23_2.png
visual_md/2.EDA_files/2.EDA_33_4.png
visual_md/2.EDA_files/2.EDA_5_4.png
visual_md/2.EDA_files/2.EDA_9_0.png
visual_md/__init__.py
visual_md/generate_dashboard.py
visual_md/skeleton.py
visual_md-0.1.6.dist-info/LICENSE.txt
visual_md-0.1.6.dist-info/WHEEL
visual_md-0.1.6.dist-info/METADATA
visual_md-0.1.6.dist-info/RECORD
