Metadata-Version: 2.1
Name: visual-md
Version: 0.1.6
Summary: 
Author: lyraxvincent
Author-email: njongevincent@gmail.com
Requires-Python: >=3.8,<4.0
Classifier: Programming Language :: Python :: 3
Classifier: Programming Language :: Python :: 3.10
Classifier: Programming Language :: Python :: 3.8
Classifier: Programming Language :: Python :: 3.9
Requires-Dist: build (>=0.8.0,<0.9.0)
